link_finder/__init__.py
link_finder/exceptions.py
link_finder/finder.py
link_finder/model.py
link_finder/utils.py
website_link_finder-0.1.0.dist-info/LICENSE
website_link_finder-0.1.0.dist-info/WHEEL
website_link_finder-0.1.0.dist-info/METADATA
website_link_finder-0.1.0.dist-info/RECORD
