Metadata-Version: 2.1
Name: website-link-finder
Version: 0.1.0
Summary: A python module to find all the links in a website
Author: Mohidul Islam
Author-email: mohidul.nu@gmail.com
Requires-Python: >=3.8,<4.0
Classifier: Programming Language :: Python :: 3
Classifier: Programming Language :: Python :: 3.10
Classifier: Programming Language :: Python :: 3.8
Classifier: Programming Language :: Python :: 3.9
Requires-Dist: beautifulsoup4 (>=4.11.1,<5.0.0)
Requires-Dist: requests (>=2.27.1,<3.0.0)
